pslib/__init__.py
pslib/client.py
pslib/commands.py
pslib/errors.py
pslib/message_managers.py
pslib/messages.py
pslib/network.py
pslib/rooms.py
pslib/state.py
pslib/utils.py
pslib-0.0.6.dist-info/LICENSE
pslib-0.0.6.dist-info/WHEEL
pslib-0.0.6.dist-info/METADATA
pslib-0.0.6.dist-info/RECORD
